cmsplugin_yandexmap
