Metadata-Version: 1.1
Name: cmsplugin-yandexmap
Version: 1.3.2
Summary: Plugin for django-cms. Yandex Map.
Home-page: http://github.com/moskrc/cmsplugin_yandexmap/
Author: Vitaliy Shishorin
Author-email: moskrc@gmail.com
License: MIT license
Download-URL: http://github.com/moskrc/cmsplugin_yandexmap/archive/master.zip
Platform: UNKNOWN
Classifier: Development Status :: 4 - Beta
Classifier: Framework :: Django
Classifier: Intended Audience :: Developers
Classifier: License :: OSI Approved :: MIT License
Classifier: Natural Language :: English
Classifier: Natural Language :: Russian
Classifier: Programming Language :: Python
Classifier: Topic :: Software Development :: Libraries :: Python Modules
Requires: django (>=1.5)
Requires: django_cms (>=3.0)
